datetime_expressions/__init__.py
datetime_expressions/expressions.py
django_datetime_expressions-0.2.0.dist-info/licenses/LICENSE
tests/__init__.py
tests/models.py
tests/test_mysql_settings.py
tests/test_postgres_settings.py
tests/test_sqlite_settings.py
tests/tests.py
django_datetime_expressions-0.2.0.dist-info/METADATA
django_datetime_expressions-0.2.0.dist-info/WHEEL
django_datetime_expressions-0.2.0.dist-info/top_level.txt
django_datetime_expressions-0.2.0.dist-info/RECORD
