Metadata-Version: 2.4
Name: django-datetime-expressions
Version: 0.2.0
Summary: Custom Django ORM expressions for datetime operations.
Author-email: towan912 <me@towan.io>
Maintainer-email: towan912 <me@towan.io>
License: MIT License
Project-URL: Bug Tracker, https://github.com/towan912/django-datetime-expressions/issues
Project-URL: Homepage, https://github.com/towan912/django-datetime-expressions
Keywords: django,datetime,expressions,orm
Classifier: Development Status :: 4 - Beta
Classifier: Framework :: Django
Classifier: Framework :: Django :: 4.2
Classifier: Framework :: Django :: 5.0
Classifier: Framework :: Django :: 5.1
Classifier: Programming Language :: Python
Classifier: Programming Language :: Python :: 3.9
Classifier: Programming Language :: Python :: 3.10
Classifier: Programming Language :: Python :: 3.11
Classifier: Programming Language :: Python :: 3.12
Classifier: Programming Language :: Python :: 3.13
Classifier: License :: OSI Approved :: MIT License
Classifier: Operating System :: OS Independent
Requires-Python: >=3.9
License-File: LICENSE
Requires-Dist: Django
Requires-Dist: python-dateutil
Requires-Dist: sqlparse
Dynamic: license-file
